ApiAeza/__init__.py
ApiAeza/aeza.py
AezaAPI-1.0.1.dist-info/LICENSE
AezaAPI-1.0.1.dist-info/METADATA
AezaAPI-1.0.1.dist-info/WHEEL
AezaAPI-1.0.1.dist-info/top_level.txt
AezaAPI-1.0.1.dist-info/RECORD
