Metadata-Version: 2.1
Name: AezaAPI
Version: 1.0.1
Summary: AezaAPI module
Home-page: https://github.com/BlxssdCoder/AezaAPI
Author: blxssd
Keywords: aeza python
Classifier: Programming Language :: Python :: 3.11
Classifier: License :: OSI Approved :: MIT License
Classifier: Operating System :: OS Independent
Requires-Python: >=3.7
License-File: LICENSE
Requires-Dist: requests (>=2.25.1)
